{"attard":{"state":"Attard"},"balzan":{"state":"Balzan"},"birgu":{"state":"Birgu"},"birkirkara":{"state":"Birkirkara"},"bir\u017cebbu\u0121a":{"state":"Bir\u017cebbu\u0121a"},"cospicua":{"state":"Cospicua"},"dingli":{"state":"Dingli"},"fgura":{"state":"Fgura"},"floriana":{"state":"Floriana"},"fontana":{"state":"Fontana"},"g\u0127ajnsielem":{"state":"G\u0127ajnsielem"},"g\u0127arg\u0127ur":{"state":"G\u0127arg\u0127ur"},"g\u0127asri":{"state":"G\u0127asri"},"g\u0127axaq":{"state":"G\u0127axaq"},"g\u017cira":{"state":"G\u017cira"},"iklin":{"state":"Iklin"},"kalkara":{"state":"Kalkara"},"ker\u010bem":{"state":"Ker\u010bem"},"kirkop":{"state":"Kirkop"},"lija":{"state":"Lija"},"luqa":{"state":"Luqa"},"marsa":{"state":"Marsa"},"marsaskala":{"state":"Marsaskala"},"marsaxlokk":{"state":"Marsaxlokk"},"msida":{"state":"Msida"},"munxar":{"state":"Munxar"},"m\u0121arr":{"state":"M\u0121arr"},"nadur":{"state":"Nadur"},"naxxar":{"state":"Naxxar"},"paola":{"state":"Paola"},"pembroke":{"state":"Pembroke"},"pieta":{"state":"Piet\u00e0"},"qala":{"state":"Qala"},"qormi":{"state":"Qormi"},"qrendi":{"state":"Qrendi"},"saint-lawrence":{"state":"Saint Lawrence"},"san-\u0121wann":{"state":"San \u0120wann"},"sannat":{"state":"Sannat"},"santa-lu\u010bija":{"state":"Santa Lu\u010bija"},"senglea":{"state":"Senglea"},"si\u0121\u0121iewi":{"state":"Si\u0121\u0121iewi"},"sliema":{"state":"Sliema"},"st.-julians":{"state":"St. Julian's"},"st.-pauls-bay":{"state":"St. Paul's Bay"},"swieqi":{"state":"Swieqi"},"ta-xbiex":{"state":"Ta' Xbiex"},"tarxien":{"state":"Tarxien"},"valletta":{"state":"Valletta"},"victoria":{"state":"Victoria"},"xag\u0127ra":{"state":"Xag\u0127ra"},"xewkija":{"state":"Xewkija"},"xg\u0127ajra":{"state":"Xg\u0127ajra"},"\u0127amrun":{"state":"\u0126amrun"},"\u017cabbar":{"state":"\u017babbar"},"\u017cebbu\u0121-gozo":{"state":"\u017bebbu\u0121 Gozo"},"\u017cebbu\u0121-malta":{"state":"\u017bebbu\u0121 Malta"},"\u017cejtun":{"state":"\u017bejtun"},"\u017currieq":{"state":"\u017burrieq"}}