{"Adjuntas":{"Adjuntas":{"state":"Puerto Rico","city":"Adjuntas","ward":"Adjuntas"}},"Aguada":{"Aguada":{"state":"Puerto Rico","city":"Aguada","ward":"Aguada"}},"Aguadilla":{"Aguadilla":{"state":"Puerto Rico","city":"Aguadilla","ward":"Aguadilla"}},"Aguas Buenas":{"Aguas Buenas":{"state":"Puerto Rico","city":"Aguas Buenas","ward":"Aguas Buenas"}},"Aguas Claras":{"Aguas Claras":{"state":"Puerto Rico","city":"Aguas Claras","ward":"Aguas Claras"}},"Aguilita":{"Aguilita":{"state":"Puerto Rico","city":"Aguilita","ward":"Aguilita"}},"Aibonito":{"Aibonito":{"state":"Puerto Rico","city":"Aibonito","ward":"Aibonito"}},"Animas":{"Animas":{"state":"Puerto Rico","city":"Animas","ward":"Animas"}},"Ant\u00f3n Ruiz":{"Ant\u00f3n Ruiz":{"state":"Puerto Rico","city":"Ant\u00f3n Ruiz","ward":"Ant\u00f3n Ruiz"}},"Arecibo":{"Arecibo":{"state":"Puerto Rico","city":"Arecibo","ward":"Arecibo"}},"Arroyo":{"Arroyo":{"state":"Puerto Rico","city":"Arroyo","ward":"Arroyo"}},"A\u00f1asco":{"A\u00f1asco":{"state":"Puerto Rico","city":"A\u00f1asco","ward":"A\u00f1asco"}},"Bairoa":{"Bairoa":{"state":"Puerto Rico","city":"Bairoa","ward":"Bairoa"}},"Bajadero":{"Bajadero":{"state":"Puerto Rico","city":"Bajadero","ward":"Bajadero"}},"Bajandas":{"Bajandas":{"state":"Puerto Rico","city":"Bajandas","ward":"Bajandas"}},"Barahona":{"Barahona":{"state":"Puerto Rico","city":"Barahona","ward":"Barahona"}},"Barceloneta":{"Barceloneta":{"state":"Puerto Rico","city":"Barceloneta","ward":"Barceloneta"}},"Barranquitas":{"Barranquitas":{"state":"Puerto Rico","city":"Barranquitas","ward":"Barranquitas"}},"Bartolo":{"Bartolo":{"state":"Puerto Rico","city":"Bartolo","ward":"Bartolo"}},"Bayamon":{"Bayamon":{"state":"Puerto Rico","city":"Bayamon","ward":"Bayamon"}},"Benitez":{"Benitez":{"state":"Puerto Rico","city":"Benitez","ward":"Benitez"}},"Betances":{"Betances":{"state":"Puerto Rico","city":"Betances","ward":"Betances"}},"Boqueron":{"Boqueron":{"state":"Puerto Rico","city":"Boqueron","ward":"Boqueron"}},"Boquer\u00f3n Cabo Rojo":{"Boquer\u00f3n Cabo Rojo":{"state":"Puerto Rico","city":"Boquer\u00f3n Cabo Rojo","ward":"Boquer\u00f3n Cabo Rojo"}},"Brenas":{"Brenas":{"state":"Puerto Rico","city":"Brenas","ward":"Brenas"}},"Buena Vista":{"Buena Vista":{"state":"Puerto Rico","city":"Buena Vista","ward":"Buena Vista"}},"Bufalo":{"Bufalo":{"state":"Puerto Rico","city":"Bufalo","ward":"Bufalo"}},"Caban":{"Caban":{"state":"Puerto Rico","city":"Caban","ward":"Caban"}},"Cabo Rojo":{"Cabo Rojo":{"state":"Puerto Rico","city":"Cabo Rojo","ward":"Cabo Rojo"}},"Cabo Rojo Municipio":{"Cabo Rojo Municipio":{"state":"Puerto Rico","city":"Cabo Rojo Municipio","ward":"Cabo Rojo Municipio"}},"Cacao":{"Cacao":{"state":"Puerto Rico","city":"Cacao","ward":"Cacao"}},"Caguas":{"Caguas":{"state":"Puerto Rico","city":"Caguas","ward":"Caguas"}},"Campanilla":{"Campanilla":{"state":"Puerto Rico","city":"Campanilla","ward":"Campanilla"}},"Campo Rico":{"Campo Rico":{"state":"Puerto Rico","city":"Campo Rico","ward":"Campo Rico"}},"Camuy":{"Camuy":{"state":"Puerto Rico","city":"Camuy","ward":"Camuy"}},"Candelaria":{"Candelaria":{"state":"Puerto Rico","city":"Candelaria","ward":"Candelaria"}},"Candelaria Arenas":{"Candelaria Arenas":{"state":"Puerto Rico","city":"Candelaria Arenas","ward":"Candelaria Arenas"}},"Candelero Arriba":{"Candelero Arriba":{"state":"Puerto Rico","city":"Candelero Arriba","ward":"Candelero Arriba"}},"Can\u00f3vanas":{"Can\u00f3vanas":{"state":"Puerto Rico","city":"Can\u00f3vanas","ward":"Can\u00f3vanas"}},"Capitanejo":{"Capitanejo":{"state":"Puerto Rico","city":"Capitanejo","ward":"Capitanejo"}},"Carolina":{"Carolina":{"state":"Puerto Rico","city":"Carolina","ward":"Carolina"}},"Carrizales":{"Carrizales":{"state":"Puerto Rico","city":"Carrizales","ward":"Carrizales"}},"Cata\u00f1o":{"Cata\u00f1o":{"state":"Puerto Rico","city":"Cata\u00f1o","ward":"Cata\u00f1o"}},"Cayey":{"Cayey":{"state":"Puerto Rico","city":"Cayey","ward":"Cayey"}},"Cayuco":{"Cayuco":{"state":"Puerto Rico","city":"Cayuco","ward":"Cayuco"}},"Ceiba":{"Ceiba":{"state":"Puerto Rico","city":"Ceiba","ward":"Ceiba"}},"Ceiba Municipio":{"Ceiba Municipio":{"state":"Puerto Rico","city":"Ceiba Municipio","ward":"Ceiba Municipio"}},"Celada":{"Celada":{"state":"Puerto Rico","city":"Celada","ward":"Celada"}},"Central Aguirre":{"Central Aguirre":{"state":"Puerto Rico","city":"Central Aguirre","ward":"Central Aguirre"}},"Ciales":{"Ciales":{"state":"Puerto Rico","city":"Ciales","ward":"Ciales"}},"Ciales Municipio":{"Ciales Municipio":{"state":"Puerto Rico","city":"Ciales Municipio","ward":"Ciales Municipio"}},"Cidra":{"Cidra":{"state":"Puerto Rico","city":"Cidra","ward":"Cidra"}},"Coamo":{"Coamo":{"state":"Puerto Rico","city":"Coamo","ward":"Coamo"}},"Coco":{"Coco":{"state":"Puerto Rico","city":"Coco","ward":"Coco"}},"Comer\u00edo":{"Comer\u00edo":{"state":"Puerto Rico","city":"Comer\u00edo","ward":"Comer\u00edo"}},"Comer\u00edo Municipio":{"Comer\u00edo Municipio":{"state":"Puerto Rico","city":"Comer\u00edo Municipio","ward":"Comer\u00edo Municipio"}},"Comunas":{"Comunas":{"state":"Puerto Rico","city":"Comunas","ward":"Comunas"}},"Coqu\u00ed":{"Coqu\u00ed":{"state":"Puerto Rico","city":"Coqu\u00ed","ward":"Coqu\u00ed"}},"Coraz\u00f3n":{"Coraz\u00f3n":{"state":"Puerto Rico","city":"Coraz\u00f3n","ward":"Coraz\u00f3n"}},"Corcovado":{"Corcovado":{"state":"Puerto Rico","city":"Corcovado","ward":"Corcovado"}},"Corozal":{"Corozal":{"state":"Puerto Rico","city":"Corozal","ward":"Corozal"}},"Corozal Municipio":{"Corozal Municipio":{"state":"Puerto Rico","city":"Corozal Municipio","ward":"Corozal Municipio"}},"Coto Laurel":{"Coto Laurel":{"state":"Puerto Rico","city":"Coto Laurel","ward":"Coto Laurel"}},"Coto Norte":{"Coto Norte":{"state":"Puerto Rico","city":"Coto Norte","ward":"Coto Norte"}},"Culebra":{"Culebra":{"state":"Puerto Rico","city":"Culebra","ward":"Culebra"}},"Culebra barrio-pueblo":{"Culebra barrio-pueblo":{"state":"Puerto Rico","city":"Culebra barrio-pueblo","ward":"Culebra barrio-pueblo"}},"Daguao":{"Daguao":{"state":"Puerto Rico","city":"Daguao","ward":"Daguao"}},"Dorado":{"Dorado":{"state":"Puerto Rico","city":"Dorado","ward":"Dorado"}},"Dorado Municipio":{"Dorado Municipio":{"state":"Puerto Rico","city":"Dorado Municipio","ward":"Dorado Municipio"}},"El Mang\u00f3":{"El Mang\u00f3":{"state":"Puerto Rico","city":"El Mang\u00f3","ward":"El Mang\u00f3"}},"El Negro":{"El Negro":{"state":"Puerto Rico","city":"El Negro","ward":"El Negro"}},"El Ojo":{"El Ojo":{"state":"Puerto Rico","city":"El Ojo","ward":"El Ojo"}},"Emajagua":{"Emajagua":{"state":"Puerto Rico","city":"Emajagua","ward":"Emajagua"}},"Esperanza":{"Esperanza":{"state":"Puerto Rico","city":"Esperanza","ward":"Esperanza"}},"Espino":{"Espino":{"state":"Puerto Rico","city":"Espino","ward":"Espino"}},"Estancias de Florida":{"Estancias de Florida":{"state":"Puerto Rico","city":"Estancias de Florida","ward":"Estancias de Florida"}},"Fajardo":{"Fajardo":{"state":"Puerto Rico","city":"Fajardo","ward":"Fajardo"}},"Fajardo Municipio":{"Fajardo Municipio":{"state":"Puerto Rico","city":"Fajardo Municipio","ward":"Fajardo Municipio"}},"Florida":{"Florida":{"state":"Puerto Rico","city":"Florida","ward":"Florida"}},"Franquez":{"Franquez":{"state":"Puerto Rico","city":"Franquez","ward":"Franquez"}},"Fuig":{"Fuig":{"state":"Puerto Rico","city":"Fuig","ward":"Fuig"}},"G. L. Garcia":{"G. L. Garcia":{"state":"Puerto Rico","city":"G. L. Garcia","ward":"G. L. Garcia"}},"Galateo":{"Galateo":{"state":"Puerto Rico","city":"Galateo","ward":"Galateo"}},"Garrochales":{"Garrochales":{"state":"Puerto Rico","city":"Garrochales","ward":"Garrochales"}},"Guayabal":{"Guayabal":{"state":"Puerto Rico","city":"Guayabal","ward":"Guayabal"}},"Guayama":{"Guayama":{"state":"Puerto Rico","city":"Guayama","ward":"Guayama"}},"Guayama Municipio":{"Guayama Municipio":{"state":"Puerto Rico","city":"Guayama Municipio","ward":"Guayama Municipio"}},"Guayanilla":{"Guayanilla":{"state":"Puerto Rico","city":"Guayanilla","ward":"Guayanilla"}},"Guaynabo":{"Guaynabo":{"state":"Puerto Rico","city":"Guaynabo","ward":"Guaynabo"}},"Gurabo":{"Gurabo":{"state":"Puerto Rico","city":"Gurabo","ward":"Gurabo"}},"Gurabo Municipio":{"Gurabo Municipio":{"state":"Puerto Rico","city":"Gurabo Municipio","ward":"Gurabo Municipio"}},"Gu\u00e1nica":{"Gu\u00e1nica":{"state":"Puerto Rico","city":"Gu\u00e1nica","ward":"Gu\u00e1nica"}},"Gu\u00e1nica Municipio":{"Gu\u00e1nica Municipio":{"state":"Puerto Rico","city":"Gu\u00e1nica Municipio","ward":"Gu\u00e1nica Municipio"}},"H. Rivera Colon":{"H. Rivera Colon":{"state":"Puerto Rico","city":"H. Rivera Colon","ward":"H. Rivera Colon"}},"Hatillo":{"Hatillo":{"state":"Puerto Rico","city":"Hatillo","ward":"Hatillo"}},"Hatillo Municipio":{"Hatillo Municipio":{"state":"Puerto Rico","city":"Hatillo Municipio","ward":"Hatillo Municipio"}},"Hato Arriba":{"Hato Arriba":{"state":"Puerto Rico","city":"Hato Arriba","ward":"Hato Arriba"}},"Hato Candal":{"Hato Candal":{"state":"Puerto Rico","city":"Hato Candal","ward":"Hato Candal"}},"Hormigueros":{"Hormigueros":{"state":"Puerto Rico","city":"Hormigueros","ward":"Hormigueros"}},"Hormigueros Municipio":{"Hormigueros Municipio":{"state":"Puerto Rico","city":"Hormigueros Municipio","ward":"Hormigueros Municipio"}},"Humacao":{"Humacao":{"state":"Puerto Rico","city":"Humacao","ward":"Humacao"}},"Imbery":{"Imbery":{"state":"Puerto Rico","city":"Imbery","ward":"Imbery"}},"Indios":{"Indios":{"state":"Puerto Rico","city":"Indios","ward":"Indios"}},"Ingenio":{"Ingenio":{"state":"Puerto Rico","city":"Ingenio","ward":"Ingenio"}},"Isabel Segunda":{"Isabel Segunda":{"state":"Puerto Rico","city":"Isabel Segunda","ward":"Isabel Segunda"}},"Isabela":{"Isabela":{"state":"Puerto Rico","city":"Isabela","ward":"Isabela"}},"Jagual":{"Jagual":{"state":"Puerto Rico","city":"Jagual","ward":"Jagual"}},"Jauca":{"Jauca":{"state":"Puerto Rico","city":"Jauca","ward":"Jauca"}},"Jayuya":{"Jayuya":{"state":"Puerto Rico","city":"Jayuya","ward":"Jayuya"}},"Jobos":{"Jobos":{"state":"Puerto Rico","city":"Jobos","ward":"Jobos"}},"Juana D\u00edaz":{"Juana D\u00edaz":{"state":"Puerto Rico","city":"Juana D\u00edaz","ward":"Juana D\u00edaz"}},"Juana D\u00edaz Municipio":{"Juana D\u00edaz Municipio":{"state":"Puerto Rico","city":"Juana D\u00edaz Municipio","ward":"Juana D\u00edaz Municipio"}},"Juncal":{"Juncal":{"state":"Puerto Rico","city":"Juncal","ward":"Juncal"}},"Juncos":{"Juncos":{"state":"Puerto Rico","city":"Juncos","ward":"Juncos"}},"La Alianza":{"La Alianza":{"state":"Puerto Rico","city":"La Alianza","ward":"La Alianza"}},"La Dolores":{"La Dolores":{"state":"Puerto Rico","city":"La Dolores","ward":"La Dolores"}},"La Fermina":{"La Fermina":{"state":"Puerto Rico","city":"La Fermina","ward":"La Fermina"}},"La Luisa":{"La Luisa":{"state":"Puerto Rico","city":"La Luisa","ward":"La Luisa"}},"La Parguera":{"La Parguera":{"state":"Puerto Rico","city":"La Parguera","ward":"La Parguera"}},"La Playa":{"La Playa":{"state":"Puerto Rico","city":"La Playa","ward":"La Playa"}},"La Plena":{"La Plena":{"state":"Puerto Rico","city":"La Plena","ward":"La Plena"}},"Lajas":{"Lajas":{"state":"Puerto Rico","city":"Lajas","ward":"Lajas"}},"Lajas Municipio":{"Lajas Municipio":{"state":"Puerto Rico","city":"Lajas Municipio","ward":"Lajas Municipio"}},"Lamboglia":{"Lamboglia":{"state":"Puerto Rico","city":"Lamboglia","ward":"Lamboglia"}},"Lares":{"Lares":{"state":"Puerto Rico","city":"Lares","ward":"Lares"}},"Las Marias":{"Las Marias":{"state":"Puerto Rico","city":"Las Marias","ward":"Las Marias"}},"Las Mar\u00edas Municipio":{"Las Mar\u00edas Municipio":{"state":"Puerto Rico","city":"Las Mar\u00edas Municipio","ward":"Las Mar\u00edas Municipio"}},"Las Ochenta":{"Las Ochenta":{"state":"Puerto Rico","city":"Las Ochenta","ward":"Las Ochenta"}},"Las Ollas":{"Las Ollas":{"state":"Puerto Rico","city":"Las Ollas","ward":"Las Ollas"}},"Las Piedras":{"Las Piedras":{"state":"Puerto Rico","city":"Las Piedras","ward":"Las Piedras"}},"Las Piedras Municipio":{"Las Piedras Municipio":{"state":"Puerto Rico","city":"Las Piedras Municipio","ward":"Las Piedras Municipio"}},"Levittown":{"Levittown":{"state":"Puerto Rico","city":"Levittown","ward":"Levittown"}},"Liborio Negron Torres":{"Liborio Negron Torres":{"state":"Puerto Rico","city":"Liborio Negron Torres","ward":"Liborio Negron Torres"}},"Lluveras":{"Lluveras":{"state":"Puerto Rico","city":"Lluveras","ward":"Lluveras"}},"Lomas":{"Lomas":{"state":"Puerto Rico","city":"Lomas","ward":"Lomas"}},"Los Llanos":{"Los Llanos":{"state":"Puerto Rico","city":"Los Llanos","ward":"Los Llanos"}},"Lo\u00edza":{"Lo\u00edza":{"state":"Puerto Rico","city":"Lo\u00edza","ward":"Lo\u00edza"}},"Luis Llor\u00e9ns Torres":{"Luis Llor\u00e9ns Torres":{"state":"Puerto Rico","city":"Luis Llor\u00e9ns Torres","ward":"Luis Llor\u00e9ns Torres"}},"Luis M. Cintron":{"Luis M. Cintron":{"state":"Puerto Rico","city":"Luis M. Cintron","ward":"Luis M. Cintron"}},"Luquillo":{"Luquillo":{"state":"Puerto Rico","city":"Luquillo","ward":"Luquillo"}},"Luquillo Municipio":{"Luquillo Municipio":{"state":"Puerto Rico","city":"Luquillo Municipio","ward":"Luquillo Municipio"}},"Luyando":{"Luyando":{"state":"Puerto Rico","city":"Luyando","ward":"Luyando"}},"Magas Arriba":{"Magas Arriba":{"state":"Puerto Rico","city":"Magas Arriba","ward":"Magas Arriba"}},"Manat\u00ed":{"Manat\u00ed":{"state":"Puerto Rico","city":"Manat\u00ed","ward":"Manat\u00ed"}},"Maria Antonia":{"Maria Antonia":{"state":"Puerto Rico","city":"Maria Antonia","ward":"Maria Antonia"}},"Mariano Col\u00f3n":{"Mariano Col\u00f3n":{"state":"Puerto Rico","city":"Mariano Col\u00f3n","ward":"Mariano Col\u00f3n"}},"Maricao":{"Maricao":{"state":"Puerto Rico","city":"Maricao","ward":"Maricao"}},"Maricao Municipio":{"Maricao Municipio":{"state":"Puerto Rico","city":"Maricao Municipio","ward":"Maricao Municipio"}},"Martorell":{"Martorell":{"state":"Puerto Rico","city":"Martorell","ward":"Martorell"}},"Marue\u00f1o":{"Marue\u00f1o":{"state":"Puerto Rico","city":"Marue\u00f1o","ward":"Marue\u00f1o"}},"Maunabo":{"Maunabo":{"state":"Puerto Rico","city":"Maunabo","ward":"Maunabo"}},"Maunabo Municipio":{"Maunabo Municipio":{"state":"Puerto Rico","city":"Maunabo Municipio","ward":"Maunabo Municipio"}},"Mayag\u00fcez":{"Mayag\u00fcez":{"state":"Puerto Rico","city":"Mayag\u00fcez","ward":"Mayag\u00fcez"}},"Miranda":{"Miranda":{"state":"Puerto Rico","city":"Miranda","ward":"Miranda"}},"Moca":{"Moca":{"state":"Puerto Rico","city":"Moca","ward":"Moca"}},"Moca Municipio":{"Moca Municipio":{"state":"Puerto Rico","city":"Moca Municipio","ward":"Moca Municipio"}},"Monserrate":{"Monserrate":{"state":"Puerto Rico","city":"Monserrate","ward":"Monserrate"}},"Monte Grande":{"Monte Grande":{"state":"Puerto Rico","city":"Monte Grande","ward":"Monte Grande"}},"Mora":{"Mora":{"state":"Puerto Rico","city":"Mora","ward":"Mora"}},"Morovis":{"Morovis":{"state":"Puerto Rico","city":"Morovis","ward":"Morovis"}},"Mucarabones":{"Mucarabones":{"state":"Puerto Rico","city":"Mucarabones","ward":"Mucarabones"}},"Naguabo":{"Naguabo":{"state":"Puerto Rico","city":"Naguabo","ward":"Naguabo"}},"Naguabo Municipio":{"Naguabo Municipio":{"state":"Puerto Rico","city":"Naguabo Municipio","ward":"Naguabo Municipio"}},"Naranjito":{"Naranjito":{"state":"Puerto Rico","city":"Naranjito","ward":"Naranjito"}},"Naranjito Municipio":{"Naranjito Municipio":{"state":"Puerto Rico","city":"Naranjito Municipio","ward":"Naranjito Municipio"}},"Olimpo":{"Olimpo":{"state":"Puerto Rico","city":"Olimpo","ward":"Olimpo"}},"Orocovis":{"Orocovis":{"state":"Puerto Rico","city":"Orocovis","ward":"Orocovis"}},"Orocovis Municipio":{"Orocovis Municipio":{"state":"Puerto Rico","city":"Orocovis Municipio","ward":"Orocovis Municipio"}},"Pajonal":{"Pajonal":{"state":"Puerto Rico","city":"Pajonal","ward":"Pajonal"}},"Palmarejo":{"Palmarejo":{"state":"Puerto Rico","city":"Palmarejo","ward":"Palmarejo"}},"Palmas":{"Palmas":{"state":"Puerto Rico","city":"Palmas","ward":"Palmas"}},"Palmer":{"Palmer":{"state":"Puerto Rico","city":"Palmer","ward":"Palmer"}},"Palo Seco":{"Palo Seco":{"state":"Puerto Rico","city":"Palo Seco","ward":"Palo Seco"}},"Palomas":{"Palomas":{"state":"Puerto Rico","city":"Palomas","ward":"Palomas"}},"Parcelas La Milagrosa":{"Parcelas La Milagrosa":{"state":"Puerto Rico","city":"Parcelas La Milagrosa","ward":"Parcelas La Milagrosa"}},"Parcelas Nuevas":{"Parcelas Nuevas":{"state":"Puerto Rico","city":"Parcelas Nuevas","ward":"Parcelas Nuevas"}},"Parcelas Pe\u00f1uelas":{"Parcelas Pe\u00f1uelas":{"state":"Puerto Rico","city":"Parcelas Pe\u00f1uelas","ward":"Parcelas Pe\u00f1uelas"}},"Pastos":{"Pastos":{"state":"Puerto Rico","city":"Pastos","ward":"Pastos"}},"Patillas":{"Patillas":{"state":"Puerto Rico","city":"Patillas","ward":"Patillas"}},"Patillas Municipio":{"Patillas Municipio":{"state":"Puerto Rico","city":"Patillas Municipio","ward":"Patillas Municipio"}},"Pe\u00f1a Pobre":{"Pe\u00f1a Pobre":{"state":"Puerto Rico","city":"Pe\u00f1a Pobre","ward":"Pe\u00f1a Pobre"}},"Pe\u00f1uelas":{"Pe\u00f1uelas":{"state":"Puerto Rico","city":"Pe\u00f1uelas","ward":"Pe\u00f1uelas"}},"Piedra Gorda":{"Piedra Gorda":{"state":"Puerto Rico","city":"Piedra Gorda","ward":"Piedra Gorda"}},"Playa Fortuna":{"Playa Fortuna":{"state":"Puerto Rico","city":"Playa Fortuna","ward":"Playa Fortuna"}},"Playita":{"Playita":{"state":"Puerto Rico","city":"Playita","ward":"Playita"}},"Playita Cortada":{"Playita Cortada":{"state":"Puerto Rico","city":"Playita Cortada","ward":"Playita Cortada"}},"Pole Ojea":{"Pole Ojea":{"state":"Puerto Rico","city":"Pole Ojea","ward":"Pole Ojea"}},"Ponce":{"Ponce":{"state":"Puerto Rico","city":"Ponce","ward":"Ponce"}},"Potala Pastillo":{"Potala Pastillo":{"state":"Puerto Rico","city":"Potala Pastillo","ward":"Potala Pastillo"}},"Pueblito del Rio":{"Pueblito del Rio":{"state":"Puerto Rico","city":"Pueblito del Rio","ward":"Pueblito del Rio"}},"Puerto Real":{"Puerto Real":{"state":"Puerto Rico","city":"Puerto Real","ward":"Puerto Real"}},"Punta Santiago":{"Punta Santiago":{"state":"Puerto Rico","city":"Punta Santiago","ward":"Punta Santiago"}},"P\u00e1jaros":{"P\u00e1jaros":{"state":"Puerto Rico","city":"P\u00e1jaros","ward":"P\u00e1jaros"}},"Quebrada":{"Quebrada":{"state":"Puerto Rico","city":"Quebrada","ward":"Quebrada"}},"Quebradillas":{"Quebradillas":{"state":"Puerto Rico","city":"Quebradillas","ward":"Quebradillas"}},"Quebradillas Municipio":{"Quebradillas Municipio":{"state":"Puerto Rico","city":"Quebradillas Municipio","ward":"Quebradillas Municipio"}},"Rafael Capo":{"Rafael Capo":{"state":"Puerto Rico","city":"Rafael Capo","ward":"Rafael Capo"}},"Rafael Gonzalez":{"Rafael Gonzalez":{"state":"Puerto Rico","city":"Rafael Gonzalez","ward":"Rafael Gonzalez"}},"Rafael Hernandez":{"Rafael Hernandez":{"state":"Puerto Rico","city":"Rafael Hernandez","ward":"Rafael Hernandez"}},"Ramos":{"Ramos":{"state":"Puerto Rico","city":"Ramos","ward":"Ramos"}},"Rinc\u00f3n":{"Rinc\u00f3n":{"state":"Puerto Rico","city":"Rinc\u00f3n","ward":"Rinc\u00f3n"}},"Rinc\u00f3n Municipio":{"Rinc\u00f3n Municipio":{"state":"Puerto Rico","city":"Rinc\u00f3n Municipio","ward":"Rinc\u00f3n Municipio"}},"Rio Lajas":{"Rio Lajas":{"state":"Puerto Rico","city":"Rio Lajas","ward":"Rio Lajas"}},"Rosa Sanchez":{"Rosa Sanchez":{"state":"Puerto Rico","city":"Rosa Sanchez","ward":"Rosa Sanchez"}},"R\u00edo Blanco":{"R\u00edo Blanco":{"state":"Puerto Rico","city":"R\u00edo Blanco","ward":"R\u00edo Blanco"}},"R\u00edo Ca\u00f1as Abajo":{"R\u00edo Ca\u00f1as Abajo":{"state":"Puerto Rico","city":"R\u00edo Ca\u00f1as Abajo","ward":"R\u00edo Ca\u00f1as Abajo"}},"R\u00edo Grande":{"R\u00edo Grande":{"state":"Puerto Rico","city":"R\u00edo Grande","ward":"R\u00edo Grande"}},"R\u00edo Grande Municipio":{"R\u00edo Grande Municipio":{"state":"Puerto Rico","city":"R\u00edo Grande Municipio","ward":"R\u00edo Grande Municipio"}},"R\u00edo Piedras":{"R\u00edo Piedras":{"state":"Puerto Rico","city":"R\u00edo Piedras","ward":"R\u00edo Piedras"}},"Sabana":{"Sabana":{"state":"Puerto Rico","city":"Sabana","ward":"Sabana"}},"Sabana Eneas":{"Sabana Eneas":{"state":"Puerto Rico","city":"Sabana Eneas","ward":"Sabana Eneas"}},"Sabana Grande":{"Sabana Grande":{"state":"Puerto Rico","city":"Sabana Grande","ward":"Sabana Grande"}},"Sabana Grande Municipio":{"Sabana Grande Municipio":{"state":"Puerto Rico","city":"Sabana Grande Municipio","ward":"Sabana Grande Municipio"}},"Sabana Hoyos":{"Sabana Hoyos":{"state":"Puerto Rico","city":"Sabana Hoyos","ward":"Sabana Hoyos"}},"Sabana Seca":{"Sabana Seca":{"state":"Puerto Rico","city":"Sabana Seca","ward":"Sabana Seca"}},"Salinas":{"Salinas":{"state":"Puerto Rico","city":"Salinas","ward":"Salinas"}},"San Antonio":{"San Antonio":{"state":"Puerto Rico","city":"San Antonio","ward":"San Antonio"}},"San Germ\u00e1n Municipio":{"San Germ\u00e1n Municipio":{"state":"Puerto Rico","city":"San Germ\u00e1n Municipio","ward":"San Germ\u00e1n Municipio"}},"San Isidro":{"San Isidro":{"state":"Puerto Rico","city":"San Isidro","ward":"San Isidro"}},"San Jos\u00e9":{"San Jos\u00e9":{"state":"Puerto Rico","city":"San Jos\u00e9","ward":"San Jos\u00e9"}},"San Juan":{"San Juan":{"state":"Puerto Rico","city":"San Juan","ward":"San Juan"}},"San Lorenzo":{"San Lorenzo":{"state":"Puerto Rico","city":"San Lorenzo","ward":"San Lorenzo"}},"San Sebasti\u00e1n":{"San Sebasti\u00e1n":{"state":"Puerto Rico","city":"San Sebasti\u00e1n","ward":"San Sebasti\u00e1n"}},"Santa Barbara":{"Santa Barbara":{"state":"Puerto Rico","city":"Santa Barbara","ward":"Santa Barbara"}},"Santa Clara":{"Santa Clara":{"state":"Puerto Rico","city":"Santa Clara","ward":"Santa Clara"}},"Santa Isabel":{"Santa Isabel":{"state":"Puerto Rico","city":"Santa Isabel","ward":"Santa Isabel"}},"Santa Isabel Municipio":{"Santa Isabel Municipio":{"state":"Puerto Rico","city":"Santa Isabel Municipio","ward":"Santa Isabel Municipio"}},"Santo Domingo":{"Santo Domingo":{"state":"Puerto Rico","city":"Santo Domingo","ward":"Santo Domingo"}},"Santurce":{"Santurce":{"state":"Puerto Rico","city":"Santurce","ward":"Santurce"}},"Stella":{"Stella":{"state":"Puerto Rico","city":"Stella","ward":"Stella"}},"Sumidero":{"Sumidero":{"state":"Puerto Rico","city":"Sumidero","ward":"Sumidero"}},"Su\u00e1rez":{"Su\u00e1rez":{"state":"Puerto Rico","city":"Su\u00e1rez","ward":"Su\u00e1rez"}},"Tallaboa":{"Tallaboa":{"state":"Puerto Rico","city":"Tallaboa","ward":"Tallaboa"}},"Tallaboa Alta":{"Tallaboa Alta":{"state":"Puerto Rico","city":"Tallaboa Alta","ward":"Tallaboa Alta"}},"Tiburones":{"Tiburones":{"state":"Puerto Rico","city":"Tiburones","ward":"Tiburones"}},"Tierras Nuevas Poniente":{"Tierras Nuevas Poniente":{"state":"Puerto Rico","city":"Tierras Nuevas Poniente","ward":"Tierras Nuevas Poniente"}},"Toa Alta":{"Toa Alta":{"state":"Puerto Rico","city":"Toa Alta","ward":"Toa Alta"}},"Toa Alta Municipio":{"Toa Alta Municipio":{"state":"Puerto Rico","city":"Toa Alta Municipio","ward":"Toa Alta Municipio"}},"Toa Baja":{"Toa Baja":{"state":"Puerto Rico","city":"Toa Baja","ward":"Toa Baja"}},"Trujillo Alto":{"Trujillo Alto":{"state":"Puerto Rico","city":"Trujillo Alto","ward":"Trujillo Alto"}},"Trujillo Alto Municipio":{"Trujillo Alto Municipio":{"state":"Puerto Rico","city":"Trujillo Alto Municipio","ward":"Trujillo Alto Municipio"}},"Utuado":{"Utuado":{"state":"Puerto Rico","city":"Utuado","ward":"Utuado"}},"Utuado barrio-pueblo":{"Utuado barrio-pueblo":{"state":"Puerto Rico","city":"Utuado barrio-pueblo","ward":"Utuado barrio-pueblo"}},"Vega Alta":{"Vega Alta":{"state":"Puerto Rico","city":"Vega Alta","ward":"Vega Alta"}},"Vega Alta Municipio":{"Vega Alta Municipio":{"state":"Puerto Rico","city":"Vega Alta Municipio","ward":"Vega Alta Municipio"}},"Vega Baja":{"Vega Baja":{"state":"Puerto Rico","city":"Vega Baja","ward":"Vega Baja"}},"Vieques":{"Vieques":{"state":"Puerto Rico","city":"Vieques","ward":"Vieques"}},"Vieques Municipality":{"Vieques Municipality":{"state":"Puerto Rico","city":"Vieques Municipality","ward":"Vieques Municipality"}},"Villalba":{"Villalba":{"state":"Puerto Rico","city":"Villalba","ward":"Villalba"}},"Villalba Municipio":{"Villalba Municipio":{"state":"Puerto Rico","city":"Villalba Municipio","ward":"Villalba Municipio"}},"V\u00e1zquez":{"V\u00e1zquez":{"state":"Puerto Rico","city":"V\u00e1zquez","ward":"V\u00e1zquez"}},"Yabucoa":{"Yabucoa":{"state":"Puerto Rico","city":"Yabucoa","ward":"Yabucoa"}},"Yabucoa Municipio":{"Yabucoa Municipio":{"state":"Puerto Rico","city":"Yabucoa Municipio","ward":"Yabucoa Municipio"}},"Yauco":{"Yauco":{"state":"Puerto Rico","city":"Yauco","ward":"Yauco"}},"Yaurel":{"Yaurel":{"state":"Puerto Rico","city":"Yaurel","ward":"Yaurel"}}}