{"Krivogashtani":{"Krivogashtani":{"state":"Krivoga\u0161tani Municipality","city":"Krivogashtani","ward":"Krivogashtani"}},"Obr\u0161ani":{"Obr\u0161ani":{"state":"Krivoga\u0161tani Municipality","city":"Obr\u0161ani","ward":"Obr\u0161ani"}},"\u041a\u043b\u0435\u0447\u043e\u0432\u0446\u0435":{"\u041a\u043b\u0435\u0447\u043e\u0432\u0446\u0435":{"state":"Krivoga\u0161tani Municipality","city":"\u041a\u043b\u0435\u0447\u043e\u0432\u0446\u0435","ward":"\u041a\u043b\u0435\u0447\u043e\u0432\u0446\u0435"}}}