{"Aiguam\u00farcia":{"Aiguam\u00farcia":{"state":"Tarragona","city":"Aiguam\u00farcia","ward":"Aiguam\u00farcia"}},"Albinyana":{"Albinyana":{"state":"Tarragona","city":"Albinyana","ward":"Albinyana"}},"Albiol":{"Albiol":{"state":"Tarragona","city":"Albiol","ward":"Albiol"}},"Alcanar":{"Alcanar":{"state":"Tarragona","city":"Alcanar","ward":"Alcanar"}},"Alcover":{"Alcover":{"state":"Tarragona","city":"Alcover","ward":"Alcover"}},"Aldea L":{"Aldea L":{"state":"Tarragona","city":"Aldea L","ward":"Aldea L"}},"Aldover":{"Aldover":{"state":"Tarragona","city":"Aldover","ward":"Aldover"}},"Aleixar":{"Aleixar":{"state":"Tarragona","city":"Aleixar","ward":"Aleixar"}},"Alfara de Carles":{"Alfara de Carles":{"state":"Tarragona","city":"Alfara de Carles","ward":"Alfara de Carles"}},"Alforja":{"Alforja":{"state":"Tarragona","city":"Alforja","ward":"Alforja"}},"Ali\u00f3":{"Ali\u00f3":{"state":"Tarragona","city":"Ali\u00f3","ward":"Ali\u00f3"}},"Almoster":{"Almoster":{"state":"Tarragona","city":"Almoster","ward":"Almoster"}},"Altafulla":{"Altafulla":{"state":"Tarragona","city":"Altafulla","ward":"Altafulla"}},"Ametlla de Mar":{"Ametlla de Mar":{"state":"Tarragona","city":"Ametlla de Mar","ward":"Ametlla de Mar"}},"Ampolla L":{"Ampolla L":{"state":"Tarragona","city":"Ampolla L","ward":"Ampolla L"}},"Amposta":{"Amposta":{"state":"Tarragona","city":"Amposta","ward":"Amposta"}},"Arbol\u00ed":{"Arbol\u00ed":{"state":"Tarragona","city":"Arbol\u00ed","ward":"Arbol\u00ed"}},"Arbo\u00e7":{"Arbo\u00e7":{"state":"Tarragona","city":"Arbo\u00e7","ward":"Arbo\u00e7"}},"Argentera":{"Argentera":{"state":"Tarragona","city":"Argentera","ward":"Argentera"}},"Arnes":{"Arnes":{"state":"Tarragona","city":"Arnes","ward":"Arnes"}},"Asc\u00f3":{"Asc\u00f3":{"state":"Tarragona","city":"Asc\u00f3","ward":"Asc\u00f3"}},"Banyeres del Pened\u00e8s":{"Banyeres del Pened\u00e8s":{"state":"Tarragona","city":"Banyeres del Pened\u00e8s","ward":"Banyeres del Pened\u00e8s"}},"Barber\u00e0 de la Conca":{"Barber\u00e0 de la Conca":{"state":"Tarragona","city":"Barber\u00e0 de la Conca","ward":"Barber\u00e0 de la Conca"}},"Batea":{"Batea":{"state":"Tarragona","city":"Batea","ward":"Batea"}},"Bellmunt del Priorat":{"Bellmunt del Priorat":{"state":"Tarragona","city":"Bellmunt del Priorat","ward":"Bellmunt del Priorat"}},"Bellvei":{"Bellvei":{"state":"Tarragona","city":"Bellvei","ward":"Bellvei"}},"Benifallet":{"Benifallet":{"state":"Tarragona","city":"Benifallet","ward":"Benifallet"}},"Benissanet":{"Benissanet":{"state":"Tarragona","city":"Benissanet","ward":"Benissanet"}},"Bisbal de Falset":{"Bisbal de Falset":{"state":"Tarragona","city":"Bisbal de Falset","ward":"Bisbal de Falset"}},"Bisbal del Pened\u00e8s":{"Bisbal del Pened\u00e8s":{"state":"Tarragona","city":"Bisbal del Pened\u00e8s","ward":"Bisbal del Pened\u00e8s"}},"Blancafort":{"Blancafort":{"state":"Tarragona","city":"Blancafort","ward":"Blancafort"}},"Bonastre":{"Bonastre":{"state":"Tarragona","city":"Bonastre","ward":"Bonastre"}},"Borges del Camp":{"Borges del Camp":{"state":"Tarragona","city":"Borges del Camp","ward":"Borges del Camp"}},"Bot":{"Bot":{"state":"Tarragona","city":"Bot","ward":"Bot"}},"Botarell":{"Botarell":{"state":"Tarragona","city":"Botarell","ward":"Botarell"}},"Br\u00e0fim":{"Br\u00e0fim":{"state":"Tarragona","city":"Br\u00e0fim","ward":"Br\u00e0fim"}},"Cabac\u00e9s":{"Cabac\u00e9s":{"state":"Tarragona","city":"Cabac\u00e9s","ward":"Cabac\u00e9s"}},"Cabra del Camp":{"Cabra del Camp":{"state":"Tarragona","city":"Cabra del Camp","ward":"Cabra del Camp"}},"Calafell":{"Calafell":{"state":"Tarragona","city":"Calafell","ward":"Calafell"}},"Camarles":{"Camarles":{"state":"Tarragona","city":"Camarles","ward":"Camarles"}},"Cambrils":{"Cambrils":{"state":"Tarragona","city":"Cambrils","ward":"Cambrils"}},"Canonja La":{"Canonja La":{"state":"Tarragona","city":"Canonja La","ward":"Canonja La"}},"Capafonts":{"Capafonts":{"state":"Tarragona","city":"Capafonts","ward":"Capafonts"}},"Cap\u00e7anes":{"Cap\u00e7anes":{"state":"Tarragona","city":"Cap\u00e7anes","ward":"Cap\u00e7anes"}},"Caseres":{"Caseres":{"state":"Tarragona","city":"Caseres","ward":"Caseres"}},"Castellvell del Camp":{"Castellvell del Camp":{"state":"Tarragona","city":"Castellvell del Camp","ward":"Castellvell del Camp"}},"Catllar":{"Catllar":{"state":"Tarragona","city":"Catllar","ward":"Catllar"}},"Colldejou":{"Colldejou":{"state":"Tarragona","city":"Colldejou","ward":"Colldejou"}},"Conesa":{"Conesa":{"state":"Tarragona","city":"Conesa","ward":"Conesa"}},"Constant\u00ed":{"Constant\u00ed":{"state":"Tarragona","city":"Constant\u00ed","ward":"Constant\u00ed"}},"Corbera dEbre":{"Corbera dEbre":{"state":"Tarragona","city":"Corbera dEbre","ward":"Corbera dEbre"}},"Cornudella de Montsant":{"Cornudella de Montsant":{"state":"Tarragona","city":"Cornudella de Montsant","ward":"Cornudella de Montsant"}},"Creixell":{"Creixell":{"state":"Tarragona","city":"Creixell","ward":"Creixell"}},"Cunit":{"Cunit":{"state":"Tarragona","city":"Cunit","ward":"Cunit"}},"Deltebre":{"Deltebre":{"state":"Tarragona","city":"Deltebre","ward":"Deltebre"}},"Duesaig\u00fces":{"Duesaig\u00fces":{"state":"Tarragona","city":"Duesaig\u00fces","ward":"Duesaig\u00fces"}},"Espluga de Francol\u00ed":{"Espluga de Francol\u00ed":{"state":"Tarragona","city":"Espluga de Francol\u00ed","ward":"Espluga de Francol\u00ed"}},"Falset":{"Falset":{"state":"Tarragona","city":"Falset","ward":"Falset"}},"Fatarella":{"Fatarella":{"state":"Tarragona","city":"Fatarella","ward":"Fatarella"}},"Febr\u00f3":{"Febr\u00f3":{"state":"Tarragona","city":"Febr\u00f3","ward":"Febr\u00f3"}},"Figuera":{"Figuera":{"state":"Tarragona","city":"Figuera","ward":"Figuera"}},"Figuerola del Camp":{"Figuerola del Camp":{"state":"Tarragona","city":"Figuerola del Camp","ward":"Figuerola del Camp"}},"Flix":{"Flix":{"state":"Tarragona","city":"Flix","ward":"Flix"}},"For\u00e8s":{"For\u00e8s":{"state":"Tarragona","city":"For\u00e8s","ward":"For\u00e8s"}},"Freginals":{"Freginals":{"state":"Tarragona","city":"Freginals","ward":"Freginals"}},"Galera":{"Galera":{"state":"Tarragona","city":"Galera","ward":"Galera"}},"Gandesa":{"Gandesa":{"state":"Tarragona","city":"Gandesa","ward":"Gandesa"}},"Garcia":{"Garcia":{"state":"Tarragona","city":"Garcia","ward":"Garcia"}},"Garidells":{"Garidells":{"state":"Tarragona","city":"Garidells","ward":"Garidells"}},"Ginestar":{"Ginestar":{"state":"Tarragona","city":"Ginestar","ward":"Ginestar"}},"Godall":{"Godall":{"state":"Tarragona","city":"Godall","ward":"Godall"}},"Gratallops":{"Gratallops":{"state":"Tarragona","city":"Gratallops","ward":"Gratallops"}},"Guiamets":{"Guiamets":{"state":"Tarragona","city":"Guiamets","ward":"Guiamets"}},"Horta de Sant Joan":{"Horta de Sant Joan":{"state":"Tarragona","city":"Horta de Sant Joan","ward":"Horta de Sant Joan"}},"Lloar":{"Lloar":{"state":"Tarragona","city":"Lloar","ward":"Lloar"}},"Llorac":{"Llorac":{"state":"Tarragona","city":"Llorac","ward":"Llorac"}},"Lloren\u00e7 del Pened\u00e8s":{"Lloren\u00e7 del Pened\u00e8s":{"state":"Tarragona","city":"Lloren\u00e7 del Pened\u00e8s","ward":"Lloren\u00e7 del Pened\u00e8s"}},"Margalef":{"Margalef":{"state":"Tarragona","city":"Margalef","ward":"Margalef"}},"Mar\u00e7\u00e0":{"Mar\u00e7\u00e0":{"state":"Tarragona","city":"Mar\u00e7\u00e0","ward":"Mar\u00e7\u00e0"}},"Mas de Barberans":{"Mas de Barberans":{"state":"Tarragona","city":"Mas de Barberans","ward":"Mas de Barberans"}},"Masdenverge":{"Masdenverge":{"state":"Tarragona","city":"Masdenverge","ward":"Masdenverge"}},"Maslloren\u00e7":{"Maslloren\u00e7":{"state":"Tarragona","city":"Maslloren\u00e7","ward":"Maslloren\u00e7"}},"Maspujols":{"Maspujols":{"state":"Tarragona","city":"Maspujols","ward":"Maspujols"}},"Masroig":{"Masroig":{"state":"Tarragona","city":"Masroig","ward":"Masroig"}},"Mas\u00f3":{"Mas\u00f3":{"state":"Tarragona","city":"Mas\u00f3","ward":"Mas\u00f3"}},"Mil\u00e0":{"Mil\u00e0":{"state":"Tarragona","city":"Mil\u00e0","ward":"Mil\u00e0"}},"Miravet":{"Miravet":{"state":"Tarragona","city":"Miravet","ward":"Miravet"}},"Molar":{"Molar":{"state":"Tarragona","city":"Molar","ward":"Molar"}},"Mont-ral":{"Mont-ral":{"state":"Tarragona","city":"Mont-ral","ward":"Mont-ral"}},"Mont-roig del Camp":{"Mont-roig del Camp":{"state":"Tarragona","city":"Mont-roig del Camp","ward":"Mont-roig del Camp"}},"Montblanc":{"Montblanc":{"state":"Tarragona","city":"Montblanc","ward":"Montblanc"}},"Montbri\u00f3 del Camp":{"Montbri\u00f3 del Camp":{"state":"Tarragona","city":"Montbri\u00f3 del Camp","ward":"Montbri\u00f3 del Camp"}},"Montferri":{"Montferri":{"state":"Tarragona","city":"Montferri","ward":"Montferri"}},"Montmell":{"Montmell":{"state":"Tarragona","city":"Montmell","ward":"Montmell"}},"Morell":{"Morell":{"state":"Tarragona","city":"Morell","ward":"Morell"}},"Morera de Montsant":{"Morera de Montsant":{"state":"Tarragona","city":"Morera de Montsant","ward":"Morera de Montsant"}},"M\u00f3ra dEbre":{"M\u00f3ra dEbre":{"state":"Tarragona","city":"M\u00f3ra dEbre","ward":"M\u00f3ra dEbre"}},"M\u00f3ra la Nova":{"M\u00f3ra la Nova":{"state":"Tarragona","city":"M\u00f3ra la Nova","ward":"M\u00f3ra la Nova"}},"Nou de Gai\u00e0":{"Nou de Gai\u00e0":{"state":"Tarragona","city":"Nou de Gai\u00e0","ward":"Nou de Gai\u00e0"}},"Nulles":{"Nulles":{"state":"Tarragona","city":"Nulles","ward":"Nulles"}},"Pallaresos":{"Pallaresos":{"state":"Tarragona","city":"Pallaresos","ward":"Pallaresos"}},"Palma dEbre":{"Palma dEbre":{"state":"Tarragona","city":"Palma dEbre","ward":"Palma dEbre"}},"Passanant i Belltall":{"Passanant i Belltall":{"state":"Tarragona","city":"Passanant i Belltall","ward":"Passanant i Belltall"}},"Pa\u00fcls":{"Pa\u00fcls":{"state":"Tarragona","city":"Pa\u00fcls","ward":"Pa\u00fcls"}},"Perafort":{"Perafort":{"state":"Tarragona","city":"Perafort","ward":"Perafort"}},"Perell\u00f3 El":{"Perell\u00f3 El":{"state":"Tarragona","city":"Perell\u00f3 El","ward":"Perell\u00f3 El"}},"Piles Les":{"Piles Les":{"state":"Tarragona","city":"Piles Les","ward":"Piles Les"}},"Pinell de Brai":{"Pinell de Brai":{"state":"Tarragona","city":"Pinell de Brai","ward":"Pinell de Brai"}},"Pira":{"Pira":{"state":"Tarragona","city":"Pira","ward":"Pira"}},"Pla de Santa Maria":{"Pla de Santa Maria":{"state":"Tarragona","city":"Pla de Santa Maria","ward":"Pla de Santa Maria"}},"Pobla de Mafumet":{"Pobla de Mafumet":{"state":"Tarragona","city":"Pobla de Mafumet","ward":"Pobla de Mafumet"}},"Pobla de Massaluc":{"Pobla de Massaluc":{"state":"Tarragona","city":"Pobla de Massaluc","ward":"Pobla de Massaluc"}},"Pobla de Montorn\u00e8s":{"Pobla de Montorn\u00e8s":{"state":"Tarragona","city":"Pobla de Montorn\u00e8s","ward":"Pobla de Montorn\u00e8s"}},"Poboleda":{"Poboleda":{"state":"Tarragona","city":"Poboleda","ward":"Poboleda"}},"Pont dArmentera":{"Pont dArmentera":{"state":"Tarragona","city":"Pont dArmentera","ward":"Pont dArmentera"}},"Pontils":{"Pontils":{"state":"Tarragona","city":"Pontils","ward":"Pontils"}},"Porrera":{"Porrera":{"state":"Tarragona","city":"Porrera","ward":"Porrera"}},"Pradell de la Teixeta":{"Pradell de la Teixeta":{"state":"Tarragona","city":"Pradell de la Teixeta","ward":"Pradell de la Teixeta"}},"Prades":{"Prades":{"state":"Tarragona","city":"Prades","ward":"Prades"}},"Prat de Comte":{"Prat de Comte":{"state":"Tarragona","city":"Prat de Comte","ward":"Prat de Comte"}},"Pratdip":{"Pratdip":{"state":"Tarragona","city":"Pratdip","ward":"Pratdip"}},"Puigpelat":{"Puigpelat":{"state":"Tarragona","city":"Puigpelat","ward":"Puigpelat"}},"Querol":{"Querol":{"state":"Tarragona","city":"Querol","ward":"Querol"}},"Rasquera":{"Rasquera":{"state":"Tarragona","city":"Rasquera","ward":"Rasquera"}},"Renau":{"Renau":{"state":"Tarragona","city":"Renau","ward":"Renau"}},"Reus":{"Reus":{"state":"Tarragona","city":"Reus","ward":"Reus"}},"Riba La":{"Riba La":{"state":"Tarragona","city":"Riba La","ward":"Riba La"}},"Riba-roja dEbre":{"Riba-roja dEbre":{"state":"Tarragona","city":"Riba-roja dEbre","ward":"Riba-roja dEbre"}},"Riera de Gai\u00e0 La":{"Riera de Gai\u00e0 La":{"state":"Tarragona","city":"Riera de Gai\u00e0 La","ward":"Riera de Gai\u00e0 La"}},"Riudecanyes":{"Riudecanyes":{"state":"Tarragona","city":"Riudecanyes","ward":"Riudecanyes"}},"Riudecols":{"Riudecols":{"state":"Tarragona","city":"Riudecols","ward":"Riudecols"}},"Riudoms":{"Riudoms":{"state":"Tarragona","city":"Riudoms","ward":"Riudoms"}},"Rocafort de Queralt":{"Rocafort de Queralt":{"state":"Tarragona","city":"Rocafort de Queralt","ward":"Rocafort de Queralt"}},"Roda de Bar\u00e0":{"Roda de Bar\u00e0":{"state":"Tarragona","city":"Roda de Bar\u00e0","ward":"Roda de Bar\u00e0"}},"Rodony\u00e0":{"Rodony\u00e0":{"state":"Tarragona","city":"Rodony\u00e0","ward":"Rodony\u00e0"}},"Roquetes":{"Roquetes":{"state":"Tarragona","city":"Roquetes","ward":"Roquetes"}},"Rourell":{"Rourell":{"state":"Tarragona","city":"Rourell","ward":"Rourell"}},"Salom\u00f3":{"Salom\u00f3":{"state":"Tarragona","city":"Salom\u00f3","ward":"Salom\u00f3"}},"Salou":{"Salou":{"state":"Tarragona","city":"Salou","ward":"Salou"}},"Sant Carles de la R\u00e0pita":{"Sant Carles de la R\u00e0pita":{"state":"Tarragona","city":"Sant Carles de la R\u00e0pita","ward":"Sant Carles de la R\u00e0pita"}},"Sant Jaume dEnveja":{"Sant Jaume dEnveja":{"state":"Tarragona","city":"Sant Jaume dEnveja","ward":"Sant Jaume dEnveja"}},"Sant Jaume dels Domenys":{"Sant Jaume dels Domenys":{"state":"Tarragona","city":"Sant Jaume dels Domenys","ward":"Sant Jaume dels Domenys"}},"Santa B\u00e1rbara":{"Santa B\u00e1rbara":{"state":"Tarragona","city":"Santa B\u00e1rbara","ward":"Santa B\u00e1rbara"}},"Santa Coloma de Queralt":{"Santa Coloma de Queralt":{"state":"Tarragona","city":"Santa Coloma de Queralt","ward":"Santa Coloma de Queralt"}},"Santa Oliva":{"Santa Oliva":{"state":"Tarragona","city":"Santa Oliva","ward":"Santa Oliva"}},"Sarral":{"Sarral":{"state":"Tarragona","city":"Sarral","ward":"Sarral"}},"Savall\u00e0 del Comtat":{"Savall\u00e0 del Comtat":{"state":"Tarragona","city":"Savall\u00e0 del Comtat","ward":"Savall\u00e0 del Comtat"}},"Secuita":{"Secuita":{"state":"Tarragona","city":"Secuita","ward":"Secuita"}},"Selva del Camp":{"Selva del Camp":{"state":"Tarragona","city":"Selva del Camp","ward":"Selva del Camp"}},"Senan":{"Senan":{"state":"Tarragona","city":"Senan","ward":"Senan"}},"Solivella":{"Solivella":{"state":"Tarragona","city":"Solivella","ward":"Solivella"}},"S\u00e9nia":{"S\u00e9nia":{"state":"Tarragona","city":"S\u00e9nia","ward":"S\u00e9nia"}},"Tarragona":{"Tarragona":{"state":"Tarragona","city":"Tarragona","ward":"Tarragona"}},"Tivenys":{"Tivenys":{"state":"Tarragona","city":"Tivenys","ward":"Tivenys"}},"Tivissa":{"Tivissa":{"state":"Tarragona","city":"Tivissa","ward":"Tivissa"}},"Torre de Espanyol":{"Torre de Espanyol":{"state":"Tarragona","city":"Torre de Espanyol","ward":"Torre de Espanyol"}},"Torre de Fontaubella":{"Torre de Fontaubella":{"state":"Tarragona","city":"Torre de Fontaubella","ward":"Torre de Fontaubella"}},"Torredembarra":{"Torredembarra":{"state":"Tarragona","city":"Torredembarra","ward":"Torredembarra"}},"Torroja del Priorat":{"Torroja del Priorat":{"state":"Tarragona","city":"Torroja del Priorat","ward":"Torroja del Priorat"}},"Tortosa":{"Tortosa":{"state":"Tarragona","city":"Tortosa","ward":"Tortosa"}},"Ulldecona":{"Ulldecona":{"state":"Tarragona","city":"Ulldecona","ward":"Ulldecona"}},"Ulldemolins":{"Ulldemolins":{"state":"Tarragona","city":"Ulldemolins","ward":"Ulldemolins"}},"Vallclara":{"Vallclara":{"state":"Tarragona","city":"Vallclara","ward":"Vallclara"}},"Vallfogona de Riucorb":{"Vallfogona de Riucorb":{"state":"Tarragona","city":"Vallfogona de Riucorb","ward":"Vallfogona de Riucorb"}},"Vallmoll":{"Vallmoll":{"state":"Tarragona","city":"Vallmoll","ward":"Vallmoll"}},"Valls":{"Valls":{"state":"Tarragona","city":"Valls","ward":"Valls"}},"Vandell\u00f2s i Hospitalet de Infant":{"Vandell\u00f2s i Hospitalet de Infant":{"state":"Tarragona","city":"Vandell\u00f2s i Hospitalet de Infant","ward":"Vandell\u00f2s i Hospitalet de Infant"}},"Vendrell":{"Vendrell":{"state":"Tarragona","city":"Vendrell","ward":"Vendrell"}},"Vespella de Gai\u00e0":{"Vespella de Gai\u00e0":{"state":"Tarragona","city":"Vespella de Gai\u00e0","ward":"Vespella de Gai\u00e0"}},"Vila-rodona":{"Vila-rodona":{"state":"Tarragona","city":"Vila-rodona","ward":"Vila-rodona"}},"Vila-seca":{"Vila-seca":{"state":"Tarragona","city":"Vila-seca","ward":"Vila-seca"}},"Vilabella":{"Vilabella":{"state":"Tarragona","city":"Vilabella","ward":"Vilabella"}},"Vilalba dels Arcs":{"Vilalba dels Arcs":{"state":"Tarragona","city":"Vilalba dels Arcs","ward":"Vilalba dels Arcs"}},"Vilallonga del Camp":{"Vilallonga del Camp":{"state":"Tarragona","city":"Vilallonga del Camp","ward":"Vilallonga del Camp"}},"Vilanova dEscornalbou":{"Vilanova dEscornalbou":{"state":"Tarragona","city":"Vilanova dEscornalbou","ward":"Vilanova dEscornalbou"}},"Vilanova de Prades":{"Vilanova de Prades":{"state":"Tarragona","city":"Vilanova de Prades","ward":"Vilanova de Prades"}},"Vilaplana":{"Vilaplana":{"state":"Tarragona","city":"Vilaplana","ward":"Vilaplana"}},"Vilaverd":{"Vilaverd":{"state":"Tarragona","city":"Vilaverd","ward":"Vilaverd"}},"Vilella Alta La":{"Vilella Alta La":{"state":"Tarragona","city":"Vilella Alta La","ward":"Vilella Alta La"}},"Vilella Baixa La":{"Vilella Baixa La":{"state":"Tarragona","city":"Vilella Baixa La","ward":"Vilella Baixa La"}},"Vimbod\u00ed i Poblet":{"Vimbod\u00ed i Poblet":{"state":"Tarragona","city":"Vimbod\u00ed i Poblet","ward":"Vimbod\u00ed i Poblet"}},"Vinebre":{"Vinebre":{"state":"Tarragona","city":"Vinebre","ward":"Vinebre"}},"Vinyols i els Arcs":{"Vinyols i els Arcs":{"state":"Tarragona","city":"Vinyols i els Arcs","ward":"Vinyols i els Arcs"}},"Xerta":{"Xerta":{"state":"Tarragona","city":"Xerta","ward":"Xerta"}}}