{"Dishn\u0101":{"Dishn\u0101":{"state":"Qena","city":"Dishn\u0101","ward":"Dishn\u0101"}},"Farsh\u016b\u0163":{"Farsh\u016b\u0163":{"state":"Qena","city":"Farsh\u016b\u0163","ward":"Farsh\u016b\u0163"}},"Isn\u0101":{"Isn\u0101":{"state":"Qena","city":"Isn\u0101","ward":"Isn\u0101"}},"Kousa":{"Kousa":{"state":"Qena","city":"Kousa","ward":"Kousa"}},"Naja' \u1e24amm\u0101d\u012b":{"Naja' \u1e24amm\u0101d\u012b":{"state":"Qena","city":"Naja' \u1e24amm\u0101d\u012b","ward":"Naja' \u1e24amm\u0101d\u012b"}},"Qin\u0101":{"Qin\u0101":{"state":"Qena","city":"Qin\u0101","ward":"Qin\u0101"}}}