{"10th of Ramadan":{"10th of Ramadan":{"state":"Sharqia","city":"10th of Ramadan","ward":"10th of Ramadan"}},"Al Qurein":{"Al Qurein":{"state":"Sharqia","city":"Al Qurein","ward":"Al Qurein"}},"Awlad Saqr":{"Awlad Saqr":{"state":"Sharqia","city":"Awlad Saqr","ward":"Awlad Saqr"}},"Bilbeis":{"Bilbeis":{"state":"Sharqia","city":"Bilbeis","ward":"Bilbeis"}},"Diyarb Negm":{"Diyarb Negm":{"state":"Sharqia","city":"Diyarb Negm","ward":"Diyarb Negm"}},"El Husseiniya":{"El Husseiniya":{"state":"Sharqia","city":"El Husseiniya","ward":"El Husseiniya"}},"Faqous":{"Faqous":{"state":"Sharqia","city":"Faqous","ward":"Faqous"}},"Hihya":{"Hihya":{"state":"Sharqia","city":"Hihya","ward":"Hihya"}},"Kafr Saqr":{"Kafr Saqr":{"state":"Sharqia","city":"Kafr Saqr","ward":"Kafr Saqr"}},"Markaz Ab\u016b \u1e28amm\u0101d":{"Markaz Ab\u016b \u1e28amm\u0101d":{"state":"Sharqia","city":"Markaz Ab\u016b \u1e28amm\u0101d","ward":"Markaz Ab\u016b \u1e28amm\u0101d"}},"Mashtoul El Souk":{"Mashtoul El Souk":{"state":"Sharqia","city":"Mashtoul El Souk","ward":"Mashtoul El Souk"}},"Minya El Qamh":{"Minya El Qamh":{"state":"Sharqia","city":"Minya El Qamh","ward":"Minya El Qamh"}},"New Salhia":{"New Salhia":{"state":"Sharqia","city":"New Salhia","ward":"New Salhia"}},"Zagazig":{"Zagazig":{"state":"Sharqia","city":"Zagazig","ward":"Zagazig"}}}