{"Ch\u012bras":{"Ch\u012bras":{"state":"Sar-e Pol","city":"Ch\u012bras","ward":"Ch\u012bras"}},"Larkird":{"Larkird":{"state":"Sar-e Pol","city":"Larkird","ward":"Larkird"}},"Qal\u2018ah-ye Shahr":{"Qal\u2018ah-ye Shahr":{"state":"Sar-e Pol","city":"Qal\u2018ah-ye Shahr","ward":"Qal\u2018ah-ye Shahr"}},"Sang-e Ch\u0101rak":{"Sang-e Ch\u0101rak":{"state":"Sar-e Pol","city":"Sang-e Ch\u0101rak","ward":"Sang-e Ch\u0101rak"}},"Sar-e Pul":{"Sar-e Pul":{"state":"Sar-e Pol","city":"Sar-e Pul","ward":"Sar-e Pul"}},"Tag\u0101w-B\u0101y":{"Tag\u0101w-B\u0101y":{"state":"Sar-e Pol","city":"Tag\u0101w-B\u0101y","ward":"Tag\u0101w-B\u0101y"}},"Tukz\u0101r":{"Tukz\u0101r":{"state":"Sar-e Pol","city":"Tukz\u0101r","ward":"Tukz\u0101r"}}}