{"acores":{"state":"A\u00e7ores"},"aveiro":{"state":"Aveiro"},"beja":{"state":"Beja"},"braga":{"state":"Braga"},"braganca":{"state":"Bragan\u00e7a"},"castelo-branco":{"state":"Castelo Branco"},"coimbra":{"state":"Coimbra"},"evora":{"state":"\u00c9vora"},"faro":{"state":"Faro"},"guarda":{"state":"Guarda"},"leiria":{"state":"Leiria"},"lisbon":{"state":"Lisbon"},"madeira":{"state":"Madeira"},"portalegre":{"state":"Portalegre"},"porto":{"state":"Porto"},"santarem":{"state":"Santar\u00e9m"},"setubal":{"state":"Set\u00fabal"},"viana-do-castelo":{"state":"Viana do Castelo"},"vila-real":{"state":"Vila Real"},"viseu":{"state":"Viseu"}}