{"Bera":{"Bera":{"state":"Rajshahi District","city":"Bera","ward":"Bera"}},"Bogra":{"Bogra":{"state":"Rajshahi District","city":"Bogra","ward":"Bogra"}},"Chapai Nababganj":{"Chapai Nababganj":{"state":"Rajshahi District","city":"Chapai Nababganj","ward":"Chapai Nababganj"}},"Ishurdi":{"Ishurdi":{"state":"Rajshahi District","city":"Ishurdi","ward":"Ishurdi"}},"Joypur H\u0101t":{"Joypur H\u0101t":{"state":"Rajshahi District","city":"Joypur H\u0101t","ward":"Joypur H\u0101t"}},"Joypurhat":{"Joypurhat":{"state":"Rajshahi District","city":"Joypurhat","ward":"Joypurhat"}},"Mahasthangarh":{"Mahasthangarh":{"state":"Rajshahi District","city":"Mahasthangarh","ward":"Mahasthangarh"}},"Naogaon":{"Naogaon":{"state":"Rajshahi District","city":"Naogaon","ward":"Naogaon"}},"Natore":{"Natore":{"state":"Rajshahi District","city":"Natore","ward":"Natore"}},"Naw\u0101bganj":{"Naw\u0101bganj":{"state":"Rajshahi District","city":"Naw\u0101bganj","ward":"Naw\u0101bganj"}},"Pabna":{"Pabna":{"state":"Rajshahi District","city":"Pabna","ward":"Pabna"}},"Puthia":{"Puthia":{"state":"Rajshahi District","city":"Puthia","ward":"Puthia"}},"P\u0101r Naogaon":{"P\u0101r Naogaon":{"state":"Rajshahi District","city":"P\u0101r Naogaon","ward":"P\u0101r Naogaon"}},"Rajshahi":{"Rajshahi":{"state":"Rajshahi District","city":"Rajshahi","ward":"Rajshahi"}},"Saidpur":{"Saidpur":{"state":"Rajshahi District","city":"Saidpur","ward":"Saidpur"}},"Shibganj":{"Shibganj":{"state":"Rajshahi District","city":"Shibganj","ward":"Shibganj"}},"Sh\u0101hz\u0101dpur":{"Sh\u0101hz\u0101dpur":{"state":"Rajshahi District","city":"Sh\u0101hz\u0101dpur","ward":"Sh\u0101hz\u0101dpur"}},"Sirajganj":{"Sirajganj":{"state":"Rajshahi District","city":"Sirajganj","ward":"Sirajganj"}}}