{"Arkhangel\u2019sk":{"Arkhangel\u2019sk":{"state":"Arkhangelsk","city":"Arkhangel\u2019sk","ward":"Arkhangel\u2019sk"}},"Ber\u00ebznik":{"Ber\u00ebznik":{"state":"Arkhangelsk","city":"Ber\u00ebznik","ward":"Ber\u00ebznik"}},"Cheremushskiy":{"Cheremushskiy":{"state":"Arkhangelsk","city":"Cheremushskiy","ward":"Cheremushskiy"}},"Dvinskoy":{"Dvinskoy":{"state":"Arkhangelsk","city":"Dvinskoy","ward":"Dvinskoy"}},"Ileza":{"Ileza":{"state":"Arkhangelsk","city":"Ileza","ward":"Ileza"}},"Il\u2019insko-Podomskoye":{"Il\u2019insko-Podomskoye":{"state":"Arkhangelsk","city":"Il\u2019insko-Podomskoye","ward":"Il\u2019insko-Podomskoye"}},"Isakogorka":{"Isakogorka":{"state":"Arkhangelsk","city":"Isakogorka","ward":"Isakogorka"}},"Kamenka":{"Kamenka":{"state":"Arkhangelsk","city":"Kamenka","ward":"Kamenka"}},"Kargopol\u2019":{"Kargopol\u2019":{"state":"Arkhangelsk","city":"Kargopol\u2019","ward":"Kargopol\u2019"}},"Kargopol\u2019skiy Rayon":{"Kargopol\u2019skiy Rayon":{"state":"Arkhangelsk","city":"Kargopol\u2019skiy Rayon","ward":"Kargopol\u2019skiy Rayon"}},"Karpogory":{"Karpogory":{"state":"Arkhangelsk","city":"Karpogory","ward":"Karpogory"}},"Katunino":{"Katunino":{"state":"Arkhangelsk","city":"Katunino","ward":"Katunino"}},"Kharitonovo":{"Kharitonovo":{"state":"Arkhangelsk","city":"Kharitonovo","ward":"Kharitonovo"}},"Kholmogorskiy Rayon":{"Kholmogorskiy Rayon":{"state":"Arkhangelsk","city":"Kholmogorskiy Rayon","ward":"Kholmogorskiy Rayon"}},"Kholmogory":{"Kholmogory":{"state":"Arkhangelsk","city":"Kholmogory","ward":"Kholmogory"}},"Kizema":{"Kizema":{"state":"Arkhangelsk","city":"Kizema","ward":"Kizema"}},"Kodino":{"Kodino":{"state":"Arkhangelsk","city":"Kodino","ward":"Kodino"}},"Konosha":{"Konosha":{"state":"Arkhangelsk","city":"Konosha","ward":"Konosha"}},"Kon\u00ebvo":{"Kon\u00ebvo":{"state":"Arkhangelsk","city":"Kon\u00ebvo","ward":"Kon\u00ebvo"}},"Koryazhma":{"Koryazhma":{"state":"Arkhangelsk","city":"Koryazhma","ward":"Koryazhma"}},"Kotlas":{"Kotlas":{"state":"Arkhangelsk","city":"Kotlas","ward":"Kotlas"}},"Kotlasskiy Rayon":{"Kotlasskiy Rayon":{"state":"Arkhangelsk","city":"Kotlasskiy Rayon","ward":"Kotlasskiy Rayon"}},"Krasnoborsk":{"Krasnoborsk":{"state":"Arkhangelsk","city":"Krasnoborsk","ward":"Krasnoborsk"}},"Kuloy":{"Kuloy":{"state":"Arkhangelsk","city":"Kuloy","ward":"Kuloy"}},"Lenskiy Rayon":{"Lenskiy Rayon":{"state":"Arkhangelsk","city":"Lenskiy Rayon","ward":"Lenskiy Rayon"}},"Leshukonskiy Rayon":{"Leshukonskiy Rayon":{"state":"Arkhangelsk","city":"Leshukonskiy Rayon","ward":"Leshukonskiy Rayon"}},"Leshukonskoye":{"Leshukonskoye":{"state":"Arkhangelsk","city":"Leshukonskoye","ward":"Leshukonskoye"}},"Loyga":{"Loyga":{"state":"Arkhangelsk","city":"Loyga","ward":"Loyga"}},"Lukovetskiy":{"Lukovetskiy":{"state":"Arkhangelsk","city":"Lukovetskiy","ward":"Lukovetskiy"}},"Mezenskiy Rayon":{"Mezenskiy Rayon":{"state":"Arkhangelsk","city":"Mezenskiy Rayon","ward":"Mezenskiy Rayon"}},"Mezen\u2019":{"Mezen\u2019":{"state":"Arkhangelsk","city":"Mezen\u2019","ward":"Mezen\u2019"}},"Mirnyy":{"Mirnyy":{"state":"Arkhangelsk","city":"Mirnyy","ward":"Mirnyy"}},"Novodvinsk":{"Novodvinsk":{"state":"Arkhangelsk","city":"Novodvinsk","ward":"Novodvinsk"}},"Nyandoma":{"Nyandoma":{"state":"Arkhangelsk","city":"Nyandoma","ward":"Nyandoma"}},"Nyandomskiy Rayon":{"Nyandomskiy Rayon":{"state":"Arkhangelsk","city":"Nyandomskiy Rayon","ward":"Nyandomskiy Rayon"}},"Oksovskiy":{"Oksovskiy":{"state":"Arkhangelsk","city":"Oksovskiy","ward":"Oksovskiy"}},"Onega":{"Onega":{"state":"Arkhangelsk","city":"Onega","ward":"Onega"}},"Onezhskiy Rayon":{"Onezhskiy Rayon":{"state":"Arkhangelsk","city":"Onezhskiy Rayon","ward":"Onezhskiy Rayon"}},"Pinega":{"Pinega":{"state":"Arkhangelsk","city":"Pinega","ward":"Pinega"}},"Pinezhskiy Rayon":{"Pinezhskiy Rayon":{"state":"Arkhangelsk","city":"Pinezhskiy Rayon","ward":"Pinezhskiy Rayon"}},"Plesetsk":{"Plesetsk":{"state":"Arkhangelsk","city":"Plesetsk","ward":"Plesetsk"}},"Podyuga":{"Podyuga":{"state":"Arkhangelsk","city":"Podyuga","ward":"Podyuga"}},"Primorskiy Rayon":{"Primorskiy Rayon":{"state":"Arkhangelsk","city":"Primorskiy Rayon","ward":"Primorskiy Rayon"}},"Privodino":{"Privodino":{"state":"Arkhangelsk","city":"Privodino","ward":"Privodino"}},"Puksoozero":{"Puksoozero":{"state":"Arkhangelsk","city":"Puksoozero","ward":"Puksoozero"}},"Rochegda":{"Rochegda":{"state":"Arkhangelsk","city":"Rochegda","ward":"Rochegda"}},"Samoded":{"Samoded":{"state":"Arkhangelsk","city":"Samoded","ward":"Samoded"}},"Severodvinsk":{"Severodvinsk":{"state":"Arkhangelsk","city":"Severodvinsk","ward":"Severodvinsk"}},"Shalakusha":{"Shalakusha":{"state":"Arkhangelsk","city":"Shalakusha","ward":"Shalakusha"}},"Shangaly":{"Shangaly":{"state":"Arkhangelsk","city":"Shangaly","ward":"Shangaly"}},"Shenkursk":{"Shenkursk":{"state":"Arkhangelsk","city":"Shenkursk","ward":"Shenkursk"}},"Shenkurskiy Rayon":{"Shenkurskiy Rayon":{"state":"Arkhangelsk","city":"Shenkurskiy Rayon","ward":"Shenkurskiy Rayon"}},"Shipitsyno":{"Shipitsyno":{"state":"Arkhangelsk","city":"Shipitsyno","ward":"Shipitsyno"}},"Solginskiy":{"Solginskiy":{"state":"Arkhangelsk","city":"Solginskiy","ward":"Solginskiy"}},"Sol\u2019vychegodsk":{"Sol\u2019vychegodsk":{"state":"Arkhangelsk","city":"Sol\u2019vychegodsk","ward":"Sol\u2019vychegodsk"}},"Udimskiy":{"Udimskiy":{"state":"Arkhangelsk","city":"Udimskiy","ward":"Udimskiy"}},"Urdoma":{"Urdoma":{"state":"Arkhangelsk","city":"Urdoma","ward":"Urdoma"}},"Ust\u2019-Shonosha":{"Ust\u2019-Shonosha":{"state":"Arkhangelsk","city":"Ust\u2019-Shonosha","ward":"Ust\u2019-Shonosha"}},"Ust\u2019yanskiy Rayon":{"Ust\u2019yanskiy Rayon":{"state":"Arkhangelsk","city":"Ust\u2019yanskiy Rayon","ward":"Ust\u2019yanskiy Rayon"}},"Uyemskiy":{"Uyemskiy":{"state":"Arkhangelsk","city":"Uyemskiy","ward":"Uyemskiy"}},"Vas\u2019kovo":{"Vas\u2019kovo":{"state":"Arkhangelsk","city":"Vas\u2019kovo","ward":"Vas\u2019kovo"}},"Vel\u2019sk":{"Vel\u2019sk":{"state":"Arkhangelsk","city":"Vel\u2019sk","ward":"Vel\u2019sk"}},"Vel\u2019skiy Rayon":{"Vel\u2019skiy Rayon":{"state":"Arkhangelsk","city":"Vel\u2019skiy Rayon","ward":"Vel\u2019skiy Rayon"}},"Verkhnyaya Toyma":{"Verkhnyaya Toyma":{"state":"Arkhangelsk","city":"Verkhnyaya Toyma","ward":"Verkhnyaya Toyma"}},"Voloshka":{"Voloshka":{"state":"Arkhangelsk","city":"Voloshka","ward":"Voloshka"}},"Vychegodskiy":{"Vychegodskiy":{"state":"Arkhangelsk","city":"Vychegodskiy","ward":"Vychegodskiy"}},"Yagry":{"Yagry":{"state":"Arkhangelsk","city":"Yagry","ward":"Yagry"}},"Yarensk":{"Yarensk":{"state":"Arkhangelsk","city":"Yarensk","ward":"Yarensk"}},"Yemetsk":{"Yemetsk":{"state":"Arkhangelsk","city":"Yemetsk","ward":"Yemetsk"}},"Yemtsa":{"Yemtsa":{"state":"Arkhangelsk","city":"Yemtsa","ward":"Yemtsa"}},"Yertsevo":{"Yertsevo":{"state":"Arkhangelsk","city":"Yertsevo","ward":"Yertsevo"}}}