{"Admiralteisky":{"Admiralteisky":{"state":"Saint Petersburg","city":"Admiralteisky","ward":"Admiralteisky"}},"Aleksandrovskaya":{"Aleksandrovskaya":{"state":"Saint Petersburg","city":"Aleksandrovskaya","ward":"Aleksandrovskaya"}},"Avtovo":{"Avtovo":{"state":"Saint Petersburg","city":"Avtovo","ward":"Avtovo"}},"Beloostrov":{"Beloostrov":{"state":"Saint Petersburg","city":"Beloostrov","ward":"Beloostrov"}},"Centralniy":{"Centralniy":{"state":"Saint Petersburg","city":"Centralniy","ward":"Centralniy"}},"Dachnoye":{"Dachnoye":{"state":"Saint Petersburg","city":"Dachnoye","ward":"Dachnoye"}},"Frunzenskiy Rayon":{"Frunzenskiy Rayon":{"state":"Saint Petersburg","city":"Frunzenskiy Rayon","ward":"Frunzenskiy Rayon"}},"Gorelovo":{"Gorelovo":{"state":"Saint Petersburg","city":"Gorelovo","ward":"Gorelovo"}},"Grazhdanka":{"Grazhdanka":{"state":"Saint Petersburg","city":"Grazhdanka","ward":"Grazhdanka"}},"Kolomyagi":{"Kolomyagi":{"state":"Saint Petersburg","city":"Kolomyagi","ward":"Kolomyagi"}},"Kolpino":{"Kolpino":{"state":"Saint Petersburg","city":"Kolpino","ward":"Kolpino"}},"Komarovo":{"Komarovo":{"state":"Saint Petersburg","city":"Komarovo","ward":"Komarovo"}},"Komendantsky aerodrom":{"Komendantsky aerodrom":{"state":"Saint Petersburg","city":"Komendantsky aerodrom","ward":"Komendantsky aerodrom"}},"Krasnogvargeisky":{"Krasnogvargeisky":{"state":"Saint Petersburg","city":"Krasnogvargeisky","ward":"Krasnogvargeisky"}},"Krasnoye Selo":{"Krasnoye Selo":{"state":"Saint Petersburg","city":"Krasnoye Selo","ward":"Krasnoye Selo"}},"Kronshtadt":{"Kronshtadt":{"state":"Saint Petersburg","city":"Kronshtadt","ward":"Kronshtadt"}},"Kupchino":{"Kupchino":{"state":"Saint Petersburg","city":"Kupchino","ward":"Kupchino"}},"Kurortnyy Rayon":{"Kurortnyy Rayon":{"state":"Saint Petersburg","city":"Kurortnyy Rayon","ward":"Kurortnyy Rayon"}},"Kushelevka":{"Kushelevka":{"state":"Saint Petersburg","city":"Kushelevka","ward":"Kushelevka"}},"Lakhtinskiy":{"Lakhtinskiy":{"state":"Saint Petersburg","city":"Lakhtinskiy","ward":"Lakhtinskiy"}},"Levashovo":{"Levashovo":{"state":"Saint Petersburg","city":"Levashovo","ward":"Levashovo"}},"Lisiy Nos":{"Lisiy Nos":{"state":"Saint Petersburg","city":"Lisiy Nos","ward":"Lisiy Nos"}},"Lomonosov":{"Lomonosov":{"state":"Saint Petersburg","city":"Lomonosov","ward":"Lomonosov"}},"Metallostroy":{"Metallostroy":{"state":"Saint Petersburg","city":"Metallostroy","ward":"Metallostroy"}},"Molodezhnoye":{"Molodezhnoye":{"state":"Saint Petersburg","city":"Molodezhnoye","ward":"Molodezhnoye"}},"Novaya Derevnya":{"Novaya Derevnya":{"state":"Saint Petersburg","city":"Novaya Derevnya","ward":"Novaya Derevnya"}},"Obukhovo":{"Obukhovo":{"state":"Saint Petersburg","city":"Obukhovo","ward":"Obukhovo"}},"Ol\u2019gino":{"Ol\u2019gino":{"state":"Saint Petersburg","city":"Ol\u2019gino","ward":"Ol\u2019gino"}},"Ozerki":{"Ozerki":{"state":"Saint Petersburg","city":"Ozerki","ward":"Ozerki"}},"Pargolovo":{"Pargolovo":{"state":"Saint Petersburg","city":"Pargolovo","ward":"Pargolovo"}},"Pavlovsk":{"Pavlovsk":{"state":"Saint Petersburg","city":"Pavlovsk","ward":"Pavlovsk"}},"Pesochnyy":{"Pesochnyy":{"state":"Saint Petersburg","city":"Pesochnyy","ward":"Pesochnyy"}},"Peterhof":{"Peterhof":{"state":"Saint Petersburg","city":"Peterhof","ward":"Peterhof"}},"Petro-Slavyanka":{"Petro-Slavyanka":{"state":"Saint Petersburg","city":"Petro-Slavyanka","ward":"Petro-Slavyanka"}},"Petrodvorets":{"Petrodvorets":{"state":"Saint Petersburg","city":"Petrodvorets","ward":"Petrodvorets"}},"Petrogradka":{"Petrogradka":{"state":"Saint Petersburg","city":"Petrogradka","ward":"Petrogradka"}},"Pontonnyy":{"Pontonnyy":{"state":"Saint Petersburg","city":"Pontonnyy","ward":"Pontonnyy"}},"Primorskiy Rayon":{"Primorskiy Rayon":{"state":"Saint Petersburg","city":"Primorskiy Rayon","ward":"Primorskiy Rayon"}},"Pushkin":{"Pushkin":{"state":"Saint Petersburg","city":"Pushkin","ward":"Pushkin"}},"Razliv":{"Razliv":{"state":"Saint Petersburg","city":"Razliv","ward":"Razliv"}},"Repino":{"Repino":{"state":"Saint Petersburg","city":"Repino","ward":"Repino"}},"Saint Petersburg":{"Saint Petersburg":{"state":"Saint Petersburg","city":"Saint Petersburg","ward":"Saint Petersburg"}},"Sap\u00ebrnyy":{"Sap\u00ebrnyy":{"state":"Saint Petersburg","city":"Sap\u00ebrnyy","ward":"Sap\u00ebrnyy"}},"Sestroretsk":{"Sestroretsk":{"state":"Saint Petersburg","city":"Sestroretsk","ward":"Sestroretsk"}},"Shushary":{"Shushary":{"state":"Saint Petersburg","city":"Shushary","ward":"Shushary"}},"Shuvalovo":{"Shuvalovo":{"state":"Saint Petersburg","city":"Shuvalovo","ward":"Shuvalovo"}},"Solnechnoye":{"Solnechnoye":{"state":"Saint Petersburg","city":"Solnechnoye","ward":"Solnechnoye"}},"Sosnovaya Polyana":{"Sosnovaya Polyana":{"state":"Saint Petersburg","city":"Sosnovaya Polyana","ward":"Sosnovaya Polyana"}},"Sosnovka":{"Sosnovka":{"state":"Saint Petersburg","city":"Sosnovka","ward":"Sosnovka"}},"Staraya Derevnya":{"Staraya Derevnya":{"state":"Saint Petersburg","city":"Staraya Derevnya","ward":"Staraya Derevnya"}},"Strel'na":{"Strel'na":{"state":"Saint Petersburg","city":"Strel'na","ward":"Strel'na"}},"Tarkhovka":{"Tarkhovka":{"state":"Saint Petersburg","city":"Tarkhovka","ward":"Tarkhovka"}},"Tyarlevo":{"Tyarlevo":{"state":"Saint Petersburg","city":"Tyarlevo","ward":"Tyarlevo"}},"Uritsk":{"Uritsk":{"state":"Saint Petersburg","city":"Uritsk","ward":"Uritsk"}},"Ust\u2019-Izhora":{"Ust\u2019-Izhora":{"state":"Saint Petersburg","city":"Ust\u2019-Izhora","ward":"Ust\u2019-Izhora"}},"Vasileostrovskiy Rayon":{"Vasileostrovskiy Rayon":{"state":"Saint Petersburg","city":"Vasileostrovskiy Rayon","ward":"Vasileostrovskiy Rayon"}},"Vasyl'evsky Ostrov":{"Vasyl'evsky Ostrov":{"state":"Saint Petersburg","city":"Vasyl'evsky Ostrov","ward":"Vasyl'evsky Ostrov"}},"Zelenogorsk":{"Zelenogorsk":{"state":"Saint Petersburg","city":"Zelenogorsk","ward":"Zelenogorsk"}}}